Metadata-Version: 2.1
Name: facematch
Version: 1.0.0
Summary: Verifies if two photos contain the same person
Home-page: https://github.com/danielgatis/facematch
Author: Daniel Gatis
Author-email: danielgatis@gmail.com
License: UNKNOWN
Keywords: face,recoginition,photo
Platform: UNKNOWN
Classifier: License :: OSI Approved :: MIT License
Classifier: Programming Language :: Python :: 3 :: Only
Requires-Python: >=3.5, <4
